reapit_cdk/email_receiver/__init__.py
reapit_cdk/email_receiver/py.typed
reapit_cdk/email_receiver/_jsii/__init__.py
reapit_cdk/email_receiver/_jsii/email-receiver@0.1.2.jsii.tgz
reapit_cdk.email_receiver-0.1.2.dist-info/LICENSE
reapit_cdk.email_receiver-0.1.2.dist-info/METADATA
reapit_cdk.email_receiver-0.1.2.dist-info/WHEEL
reapit_cdk.email_receiver-0.1.2.dist-info/top_level.txt
reapit_cdk.email_receiver-0.1.2.dist-info/RECORD
