Metadata-Version: 2.1
Name: reapit-cdk.email-receiver
Version: 0.1.2
Summary: This construct sets up everything necessary to receive email. The emails get stored in a dynamodb table, queryable by recipient. This is designed to be used in end-to-end tests, with the [@reapit-cdk/email-receiver-client](../../libs/email-receiver-client) helper library.
Home-page: https://github.com/reapit/ts-cdk-constructs/blob/main/packages/constructs/email-receiver
Author: Josh Balfour<jbalfour@reapit.com>
License: MIT
Project-URL: Source, https://github.com/reapit/ts-cdk-constructs.git
Platform: UNKNOWN
Classifier: Intended Audience :: Developers
Classifier: Operating System :: OS Independent
Classifier: Programming Language :: JavaScript
Classifier: Programming Language :: Python :: 3 :: Only
Classifier: Programming Language :: Python :: 3.8
Classifier: Programming Language :: Python :: 3.9
Classifier: Programming Language :: Python :: 3.10
Classifier: Programming Language :: Python :: 3.11
Classifier: Typing :: Typed
Classifier: Development Status :: 5 - Production/Stable
Classifier: License :: OSI Approved
Requires-Python: ~=3.8
License-File: LICENSE
Requires-Dist: aws-cdk-lib (<3.0.0,>=2.96.2)
Requires-Dist: constructs (<11.0.0,>=10.2.70)
Requires-Dist: jsii (<2.0.0,>=1.94.0)
Requires-Dist: publication (>=0.0.3)
Requires-Dist: reapit-cdk.active-ruleset (<0.2.0,>=0.1.2)
Requires-Dist: typeguard (~=2.13.3)
